damson/__init__.py
damson/__version__.py
damson/constraint.py
damson/exception.py
damson/kernel.py
damson/support.py
damson-0.6.0.dist-info/LICENSE
damson-0.6.0.dist-info/METADATA
damson-0.6.0.dist-info/WHEEL
damson-0.6.0.dist-info/top_level.txt
damson-0.6.0.dist-info/RECORD
